setup.py
MTBF_G48/__init__.py
MTBF_G48/gaia_arguments.py
MTBF_G48/runner.py
MTBF_G48/version.py
MTBF_G48.egg-info/PKG-INFO
MTBF_G48.egg-info/SOURCES.txt
MTBF_G48.egg-info/dependency_links.txt
MTBF_G48.egg-info/requires.txt
MTBF_G48.egg-info/top_level.txt
MTBF_G48/device/__init__.py
MTBF_G48/device/adb.py
MTBF_G48/device/adb_b2g.py
MTBF_G48/device/adbmanager.py
MTBF_G48/device/errors.py
MTBF_G48/device/version.py
MTBF_G48/logging/__init__.py
MTBF_G48/logging/commandline.py
MTBF_G48/logging/logtypes.py
MTBF_G48/logging/reader.py
MTBF_G48/logging/structuredlog.py
MTBF_G48/logging/unstructuredlog.py
MTBF_G48/logging/formatters/__init__.py
MTBF_G48/logging/formatters/base.py
MTBF_G48/logging/formatters/machformatter.py
MTBF_G48/logging/formatters/process.py
MTBF_G48/logging/formatters/tbplformatter.py
MTBF_G48/logging/formatters/unittest.py
MTBF_G48/logging/formatters/xunit.py
MTBF_G48/logging/formatters/html/__init__.py
MTBF_G48/logging/formatters/html/html.py
MTBF_G48/logging/formatters/html/xmlgen.py
MTBF_G48/logging/handlers/__init__.py
MTBF_G48/logging/handlers/base.py
MTBF_G48/logging/handlers/bufferhandler.py
MTBF_G48/marionette_client/__init__.py
MTBF_G48/marionette_client/by.py
MTBF_G48/marionette_client/decorators.py
MTBF_G48/marionette_client/errors.py
MTBF_G48/marionette_client/expected.py
MTBF_G48/marionette_client/httpd.py
MTBF_G48/marionette_client/keys.py
MTBF_G48/marionette_client/marionette.py
MTBF_G48/marionette_client/transport.py
MTBF_G48/marionette_client/wait.py
MTBF_G48/mozprocess/__init__.py
MTBF_G48/mozprocess/processhandler.py
MTBF_G48/mozprocess/qijo.py
MTBF_G48/mozprocess/winprocess.py
MTBF_G48/test/__init__.py
MTBF_G48/test/case.py
MTBF_G48/test/results.py