Metadata-Version: 1.1
Name: MTBF-G48
Version: 1.0.2
Summary: marionette driver to establish connection.
Home-page: UNKNOWN
Author: shayan
Author-email: syedshayan109@gmail.com
License: MIT
Download-URL: https://pypi.org/project/mtbf_g48/
Keywords: mtbf_g48,g48
Platform: UNKNOWN
